wagtail_f_richtext/__init__.py
wagtail_f_richtext/apps.py
wagtail_f_richtext/parser.py
wagtail_f_richtext/templatetags/__init__.py
wagtail_f_richtext/templatetags/frichtext_tags.py
wagtail_f_richtext-1.2.0.dist-info/licenses/LICENSE
wagtail_f_richtext-1.2.0.dist-info/METADATA
wagtail_f_richtext-1.2.0.dist-info/WHEEL
wagtail_f_richtext-1.2.0.dist-info/top_level.txt
wagtail_f_richtext-1.2.0.dist-info/RECORD
