Metadata-Version: 2.4
Name: wagtail-f-richtext
Version: 1.2.0
Summary: An alternative Wagtail richtext filter that applies classes or styles to rich text HTML content.
Author-email: Nick Moreton <nickmoreton@me.com>
License: 
Project-URL: Repository, https://github.com/wagtail-packages/wagtail-f-richtext
Project-URL: Issues, https://github.com/wagtail-packages/wagtail-f-richtext/issues
Project-URL: Changelog, https://github.com/wagtail-packages/wagtail-f-richtext/blob/release/CHANGELOG.md
Keywords: wagtail,richtext,filter,html,class,style
Classifier: Development Status :: 5 - Production/Stable
Classifier: Intended Audience :: Developers
Classifier: License :: OSI Approved :: MIT License
Classifier: Operating System :: OS Independent
Classifier: Programming Language :: Python
Classifier: Programming Language :: Python :: 3
Classifier: Programming Language :: Python :: 3.9
Classifier: Programming Language :: Python :: 3.10
Classifier: Programming Language :: Python :: 3.11
Classifier: Programming Language :: Python :: 3.12
Classifier: Programming Language :: Python :: 3.13
Classifier: Framework :: Django
Classifier: Framework :: Django :: 4.2
Classifier: Framework :: Django :: 5.1
Classifier: Framework :: Django :: 5.2
Classifier: Framework :: Wagtail
Classifier: Framework :: Wagtail :: 5
Classifier: Framework :: Wagtail :: 6
Classifier: Framework :: Wagtail :: 7
Requires-Python: >=3.9
License-File: LICENSE
Requires-Dist: Wagtail>=5.2
Provides-Extra: development
Requires-Dist: ruff>=0.11.13; extra == "development"
Provides-Extra: testing
Requires-Dist: coverage; extra == "testing"
Dynamic: license-file
